lrbenchmark/__init__.py
lrbenchmark/dataset.py
lrbenchmark/evaluation.py
lrbenchmark/transformers.py
lrbenchmark/typing.py
lrbenchmark/utils.py
lrbenchmark-0.1.2.dist-info/LICENSE.txt
lrbenchmark-0.1.2.dist-info/METADATA
lrbenchmark-0.1.2.dist-info/WHEEL
lrbenchmark-0.1.2.dist-info/top_level.txt
lrbenchmark-0.1.2.dist-info/RECORD
