Metadata-Version: 2.1
Name: lrbenchmark
Version: 0.1.2
Summary: Benchmarking Likelihood Ratio systems
Author: Netherlands Forensics Institute
License-File: LICENSE.txt
Requires-Dist: confidence
Requires-Dist: pytest
Requires-Dist: matplotlib
Requires-Dist: scikit-learn
Requires-Dist: lir
Requires-Dist: pandas
Requires-Dist: xgboost
Requires-Dist: more-itertools
